bisHash/__init__.py
bisHash/hashing.py
bisHash1-0.1.dist-info/METADATA
bisHash1-0.1.dist-info/WHEEL
bisHash1-0.1.dist-info/top_level.txt
bisHash1-0.1.dist-info/RECORD
