Metadata-Version: 2.1
Name: bisHash1
Version: 0.1
Summary: A simple hashing algorithm library
Home-page: https://github.com/michaelIldefonso/Hashing-Algorithm
Author: Group
Author-email: your.email@example.com
Requires-Python: >=3.6
Requires-Dist: argon2-cffi
Requires-Dist: ratelimit
